CHANGELOG.md
CONTRIBUTING.md
LICENSE.txt
MANIFEST.in
README.md
requirements-dev.txt
requirements.txt
setup.py
tests.py
edn_format_debug/__init__.py
edn_format_debug/char.py
edn_format_debug/compat.py
edn_format_debug/edn_dump.py
edn_format_debug/edn_lex.py
edn_format_debug/edn_parse.py
edn_format_debug/exceptions.py
edn_format_debug/immutable_dict.py
edn_format_debug/immutable_list.py
edn_format_debug.egg-info/PKG-INFO
edn_format_debug.egg-info/SOURCES.txt
edn_format_debug.egg-info/dependency_links.txt
edn_format_debug.egg-info/requires.txt
edn_format_debug.egg-info/top_level.txt