Metadata-Version: 2.1
Name: edn-format-debug
Version: 0.1.1
Summary: Swaroop's EDN format reader and writer in Python, w/ minor debug addition.
Home-page: https://github.com/DuneLeto/edn_format
Author: DuneLeto
Author-email: duneletogit@gmail.com
License: Apache 2.0
Classifier: Development Status :: 5 - Production/Stable
Classifier: Intended Audience :: Developers
Classifier: License :: OSI Approved :: Apache Software License
Classifier: Topic :: Software Development
Classifier: Programming Language :: Python
Classifier: Programming Language :: Python :: 2
Classifier: Programming Language :: Python :: 3
Classifier: Operating System :: OS Independent
License-File: LICENSE.txt
